{
  "parent": "item/handheld",
  "textures": {
    "layer0": "terracraft:item/iron_shortsword"
  },
  "display": {
    "thirdperson_righthand": {
      "rotation": [ -80, 260, -40 ],
      "translation": [ -1, 3.5, 2.5 ],
      "scale": [ 0.8, 0.8, 0.8 ]
    },
    "thirdperson_lefthand": {
      "rotation": [ -80, -280, 40 ],
      "translation": [ -1, 3.5, 2.5 ],
      "scale": [ 0.8, 0.8, 0.8 ]
    },
    "firstperson_righthand": {
      "rotation": [ -65, -90, 25 ],
      "translation": [ 1.13, 0, 1.13],
      "scale": [ 0.60, 0.60, 0.60 ]
    },
    "firstperson_lefthand": {
      "rotation": [ -65, 90, -25 ],
      "translation": [ 1.13, 0, 1.13],
      "scale": [ 0.60, 0.60, 0.60 ]
    }
  }
}

